hhsearch_python/__init__.py
hhsearch_python-1.12.dist-info/LICENSE
hhsearch_python-1.12.dist-info/METADATA
hhsearch_python-1.12.dist-info/WHEEL
hhsearch_python-1.12.dist-info/top_level.txt
hhsearch_python-1.12.dist-info/RECORD
