Metadata-Version: 2.1
Name: hhsearch-python
Version: 1.12
Summary: A small package to deal with HHSearch files.
Home-page: https://github.com/MrRedPandabaer/hhsearch-python
Author: Tim D.
Author-email: 
License: UNKNOWN
Platform: UNKNOWN
Classifier: Programming Language :: Python :: 3.7
Classifier: License :: OSI Approved :: MIT License
Classifier: Operating System :: OS Independent
